django_compressor_autoprefixer/__init__.py
django_compressor_autoprefixer-0.0.2.data/data/LICENSE
django_compressor_autoprefixer-0.0.2.data/data/README.rst
django_compressor_autoprefixer-0.0.2.dist-info/DESCRIPTION.rst
django_compressor_autoprefixer-0.0.2.dist-info/METADATA
django_compressor_autoprefixer-0.0.2.dist-info/metadata.json
django_compressor_autoprefixer-0.0.2.dist-info/RECORD
django_compressor_autoprefixer-0.0.2.dist-info/top_level.txt
django_compressor_autoprefixer-0.0.2.dist-info/WHEEL
