Metadata-Version: 1.0
Name: django-compressor-autoprefixer
Version: 0.0.2
Summary: Django Compressor CSS filter for autoprefixer
Home-page: https://github.com/dizballanze/django-compressor-autoprefixer
Author: Yuri Shikanov
Author-email: dizballanze@gmail.com
License: MIT
Platform: UNKNOWN
